xytoy/__init__.py
xytoy/cli.py
xytoy/py.typed
xytoy/settings.py
xytoy/c/__init__.py
xytoy/cache/__init__.py
xytoy/nb/__init__.py
xytoy-1.3.0.dist-info/LICENSE
xytoy-1.3.0.dist-info/METADATA
xytoy-1.3.0.dist-info/WHEEL
xytoy-1.3.0.dist-info/entry_points.txt
xytoy-1.3.0.dist-info/top_level.txt
xytoy-1.3.0.dist-info/RECORD
