Metadata-Version: 2.1
Name: xytoy
Version: 1.3.0
Summary: This a toybox of XY
Author-email: Xiao Yang <afe.young@gmail.com>
License: MIT
Project-URL: documentation, https://you-n-g.github.io/toy
Project-URL: issue, https://github.com/you-n-g/toy/issues
Project-URL: repository, https://github.com/you-n-g/toy
Keywords: copier-template,full-development-lifecycle,project-template,serious-scaffold
Classifier: Development Status :: 3 - Alpha
Classifier: License :: OSI Approved :: MIT License
Classifier: Operating System :: OS Independent
Classifier: Programming Language :: Python :: 3 :: Only
Classifier: Programming Language :: Python :: 3.9
Classifier: Programming Language :: Python :: 3.10
Classifier: Programming Language :: Python :: 3.11
Classifier: Programming Language :: Python :: 3.12
Classifier: Programming Language :: Python :: 3.13
Requires-Python: >=3.9
License-File: LICENSE
Requires-Dist: nbconvert >=7.16.4
Requires-Dist: nbformat >=5.10.4
Requires-Dist: pydantic-settings
Requires-Dist: typer[all]
